{"point_uuid": "652", "point_location": [5.47266149520874, -6.9884033203125, 5.046542167663574], "views": [{"point_uuid": "92", "nonfixated_pixel_x": 106, "nonfixated_pixel_y": 214, "camera_uuid": "af82fcf1c3064dcebf10126539a78d44", "view_id": 4}, {"point_uuid": "150", "nonfixated_pixel_x": 356, "nonfixated_pixel_y": 50, "camera_uuid": "7b39870ff9e44e7e8b36ead2111b5a37", "view_id": 2}, {"point_uuid": "236", "nonfixated_pixel_x": 96, "nonfixated_pixel_y": 172, "camera_uuid": "af82fcf1c3064dcebf10126539a78d44", "view_id": 6}, {"point_uuid": "271", "nonfixated_pixel_x": 50, "nonfixated_pixel_y": 256, "camera_uuid": "135cb66c848c49b1ac676429ab0ed03d", "view_id": 6}, {"point_uuid": "271", "nonfixated_pixel_x": 87, "nonfixated_pixel_y": 293, "camera_uuid": "af82fcf1c3064dcebf10126539a78d44", "view_id": 7}, {"point_uuid": "307", "nonfixated_pixel_x": 480, "nonfixated_pixel_y": 334, "camera_uuid": "7b39870ff9e44e7e8b36ead2111b5a37", "view_id": 0}, {"point_uuid": "316", "nonfixated_pixel_x": 492, "nonfixated_pixel_y": 335, "camera_uuid": "7b39870ff9e44e7e8b36ead2111b5a37", "view_id": 2}, {"point_uuid": "320", "nonfixated_pixel_x": 195, "nonfixated_pixel_y": 162, "camera_uuid": "af82fcf1c3064dcebf10126539a78d44", "view_id": 3}, {"point_uuid": "381", "nonfixated_pixel_x": 339, "nonfixated_pixel_y": 317, "camera_uuid": "af82fcf1c3064dcebf10126539a78d44", "view_id": 0}, {"point_uuid": "381", "nonfixated_pixel_x": 320, "nonfixated_pixel_y": 290, "camera_uuid": "7b39870ff9e44e7e8b36ead2111b5a37", "view_id": 1}, {"point_uuid": "405", "nonfixated_pixel_x": 108, "nonfixated_pixel_y": 148, "camera_uuid": "135cb66c848c49b1ac676429ab0ed03d", "view_id": 0}, {"point_uuid": "411", "nonfixated_pixel_x": 74, "nonfixated_pixel_y": 47, "camera_uuid": "135cb66c848c49b1ac676429ab0ed03d", "view_id": 0}, {"point_uuid": "441", "nonfixated_pixel_x": 162, "nonfixated_pixel_y": 119, "camera_uuid": "135cb66c848c49b1ac676429ab0ed03d", "view_id": 2}, {"point_uuid": "473", "nonfixated_pixel_x": 194, "nonfixated_pixel_y": 60, "camera_uuid": "135cb66c848c49b1ac676429ab0ed03d", "view_id": 0}, {"point_uuid": "473", "nonfixated_pixel_x": 224, "nonfixated_pixel_y": 119, "camera_uuid": "7b39870ff9e44e7e8b36ead2111b5a37", "view_id": 3}, {"point_uuid": "473", "nonfixated_pixel_x": 230, "nonfixated_pixel_y": 147, "camera_uuid": "af82fcf1c3064dcebf10126539a78d44", "view_id": 4}, {"point_uuid": "485", "nonfixated_pixel_x": 78, "nonfixated_pixel_y": 100, "camera_uuid": "135cb66c848c49b1ac676429ab0ed03d", "view_id": 0}, {"point_uuid": "519", "nonfixated_pixel_x": 380, "nonfixated_pixel_y": 232, "camera_uuid": "af82fcf1c3064dcebf10126539a78d44", "view_id": 2}, {"point_uuid": "519", "nonfixated_pixel_x": 417, "nonfixated_pixel_y": 238, "camera_uuid": "135cb66c848c49b1ac676429ab0ed03d", "view_id": 5}, {"point_uuid": "519", "nonfixated_pixel_x": 380, "nonfixated_pixel_y": 229, "camera_uuid": "7b39870ff9e44e7e8b36ead2111b5a37", "view_id": 6}, {"point_uuid": "525", "nonfixated_pixel_x": 258, "nonfixated_pixel_y": 163, "camera_uuid": "7b39870ff9e44e7e8b36ead2111b5a37", "view_id": 0}, {"point_uuid": "525", "nonfixated_pixel_x": 256, "nonfixated_pixel_y": 57, "camera_uuid": "135cb66c848c49b1ac676429ab0ed03d", "view_id": 1}, {"point_uuid": "525", "nonfixated_pixel_x": 260, "nonfixated_pixel_y": 150, "camera_uuid": "af82fcf1c3064dcebf10126539a78d44", "view_id": 3}, {"point_uuid": "549", "nonfixated_pixel_x": 501, "nonfixated_pixel_y": 309, "camera_uuid": "7b39870ff9e44e7e8b36ead2111b5a37", "view_id": 3}, {"point_uuid": "583", "nonfixated_pixel_x": 187, "nonfixated_pixel_y": 195, "camera_uuid": "135cb66c848c49b1ac676429ab0ed03d", "view_id": 2}, {"point_uuid": "608", "nonfixated_pixel_x": 400, "nonfixated_pixel_y": 162, "camera_uuid": "7b39870ff9e44e7e8b36ead2111b5a37", "view_id": 1}, {"point_uuid": "608", "nonfixated_pixel_x": 473, "nonfixated_pixel_y": 122, "camera_uuid": "af82fcf1c3064dcebf10126539a78d44", "view_id": 3}, {"point_uuid": "691", "nonfixated_pixel_x": 188, "nonfixated_pixel_y": 297, "camera_uuid": "7b39870ff9e44e7e8b36ead2111b5a37", "view_id": 4}, {"point_uuid": "696", "nonfixated_pixel_x": 234, "nonfixated_pixel_y": 19, "camera_uuid": "7b39870ff9e44e7e8b36ead2111b5a37", "view_id": 0}, {"point_uuid": "698", "nonfixated_pixel_x": 183, "nonfixated_pixel_y": 211, "camera_uuid": "135cb66c848c49b1ac676429ab0ed03d", "view_id": 0}, {"point_uuid": "732", "nonfixated_pixel_x": 165, "nonfixated_pixel_y": 126, "camera_uuid": "135cb66c848c49b1ac676429ab0ed03d", "view_id": 0}, {"point_uuid": "798", "nonfixated_pixel_x": 164, "nonfixated_pixel_y": 137, "camera_uuid": "af82fcf1c3064dcebf10126539a78d44", "view_id": 0}, {"point_uuid": "817", "nonfixated_pixel_x": 381, "nonfixated_pixel_y": 240, "camera_uuid": "7b39870ff9e44e7e8b36ead2111b5a37", "view_id": 2}, {"point_uuid": "817", "nonfixated_pixel_x": 465, "nonfixated_pixel_y": 231, "camera_uuid": "af82fcf1c3064dcebf10126539a78d44", "view_id": 3}, {"point_uuid": "838", "nonfixated_pixel_x": 415, "nonfixated_pixel_y": 257, "camera_uuid": "7b39870ff9e44e7e8b36ead2111b5a37", "view_id": 4}, {"point_uuid": "887", "nonfixated_pixel_x": 414, "nonfixated_pixel_y": 271, "camera_uuid": "7b39870ff9e44e7e8b36ead2111b5a37", "view_id": 0}, {"point_uuid": "891", "nonfixated_pixel_x": 116, "nonfixated_pixel_y": 23, "camera_uuid": "135cb66c848c49b1ac676429ab0ed03d", "view_id": 2}, {"point_uuid": "897", "nonfixated_pixel_x": 281, "nonfixated_pixel_y": 16, "camera_uuid": "7b39870ff9e44e7e8b36ead2111b5a37", "view_id": 4}, {"point_uuid": "913", "nonfixated_pixel_x": 94, "nonfixated_pixel_y": 37, "camera_uuid": "135cb66c848c49b1ac676429ab0ed03d", "view_id": 1}, {"point_uuid": "952", "nonfixated_pixel_x": 407, "nonfixated_pixel_y": 93, "camera_uuid": "af82fcf1c3064dcebf10126539a78d44", "view_id": 3}, {"point_uuid": "952", "nonfixated_pixel_x": 379, "nonfixated_pixel_y": 118, "camera_uuid": "7b39870ff9e44e7e8b36ead2111b5a37", "view_id": 4}, {"point_uuid": "982", "nonfixated_pixel_x": 425, "nonfixated_pixel_y": 242, "camera_uuid": "7b39870ff9e44e7e8b36ead2111b5a37", "view_id": 5}, {"point_uuid": "1041", "nonfixated_pixel_x": 2, "nonfixated_pixel_y": 331, "camera_uuid": "af82fcf1c3064dcebf10126539a78d44", "view_id": 4}, {"point_uuid": "1047", "nonfixated_pixel_x": 220, "nonfixated_pixel_y": 80, "camera_uuid": "af82fcf1c3064dcebf10126539a78d44", "view_id": 0}, {"point_uuid": "1047", "nonfixated_pixel_x": 185, "nonfixated_pixel_y": 2, "camera_uuid": "135cb66c848c49b1ac676429ab0ed03d", "view_id": 2}, {"point_uuid": "1047", "nonfixated_pixel_x": 233, "nonfixated_pixel_y": 142, "camera_uuid": "7b39870ff9e44e7e8b36ead2111b5a37", "view_id": 3}, {"point_uuid": "1161", "nonfixated_pixel_x": 477, "nonfixated_pixel_y": 126, "camera_uuid": "af82fcf1c3064dcebf10126539a78d44", "view_id": 0}, {"point_uuid": "1161", "nonfixated_pixel_x": 360, "nonfixated_pixel_y": 192, "camera_uuid": "7b39870ff9e44e7e8b36ead2111b5a37", "view_id": 2}, {"point_uuid": "1161", "nonfixated_pixel_x": 411, "nonfixated_pixel_y": 133, "camera_uuid": "135cb66c848c49b1ac676429ab0ed03d", "view_id": 3}, {"point_uuid": "1175", "nonfixated_pixel_x": 130, "nonfixated_pixel_y": 61, "camera_uuid": "135cb66c848c49b1ac676429ab0ed03d", "view_id": 0}, {"point_uuid": "1335", "nonfixated_pixel_x": 197, "nonfixated_pixel_y": 221, "camera_uuid": "135cb66c848c49b1ac676429ab0ed03d", "view_id": 0}, {"point_uuid": "1392", "nonfixated_pixel_x": 26, "nonfixated_pixel_y": 77, "camera_uuid": "135cb66c848c49b1ac676429ab0ed03d", "view_id": 4}, {"point_uuid": "1444", "nonfixated_pixel_x": 161, "nonfixated_pixel_y": 106, "camera_uuid": "135cb66c848c49b1ac676429ab0ed03d", "view_id": 2}, {"point_uuid": "1449", "nonfixated_pixel_x": 27, "nonfixated_pixel_y": 159, "camera_uuid": "135cb66c848c49b1ac676429ab0ed03d", "view_id": 0}, {"point_uuid": "1452", "nonfixated_pixel_x": 257, "nonfixated_pixel_y": 156, "camera_uuid": "135cb66c848c49b1ac676429ab0ed03d", "view_id": 0}, {"point_uuid": "1452", "nonfixated_pixel_x": 258, "nonfixated_pixel_y": 205, "camera_uuid": "af82fcf1c3064dcebf10126539a78d44", "view_id": 1}, {"point_uuid": "1452", "nonfixated_pixel_x": 257, "nonfixated_pixel_y": 215, "camera_uuid": "7b39870ff9e44e7e8b36ead2111b5a37", "view_id": 2}, {"point_uuid": "1457", "nonfixated_pixel_x": 350, "nonfixated_pixel_y": 65, "camera_uuid": "af82fcf1c3064dcebf10126539a78d44", "view_id": 1}, {"point_uuid": "1457", "nonfixated_pixel_x": 313, "nonfixated_pixel_y": 137, "camera_uuid": "7b39870ff9e44e7e8b36ead2111b5a37", "view_id": 4}, {"point_uuid": "1479", "nonfixated_pixel_x": 157, "nonfixated_pixel_y": 164, "camera_uuid": "7b39870ff9e44e7e8b36ead2111b5a37", "view_id": 3}]}