{"point_uuid": "558", "point_location": [7.455366611480713, -6.090108871459961, 1.5757837295532227], "views": [{"point_uuid": "1", "nonfixated_pixel_x": 135, "nonfixated_pixel_y": 167, "camera_uuid": "220387d869434246aa396d4d176250b3", "view_id": 1}, {"point_uuid": "9", "nonfixated_pixel_x": 38, "nonfixated_pixel_y": 164, "camera_uuid": "220387d869434246aa396d4d176250b3", "view_id": 1}, {"point_uuid": "49", "nonfixated_pixel_x": 311, "nonfixated_pixel_y": 165, "camera_uuid": "e629b23698734e38878f8b71b4ce29dc", "view_id": 0}, {"point_uuid": "101", "nonfixated_pixel_x": 71, "nonfixated_pixel_y": 268, "camera_uuid": "220387d869434246aa396d4d176250b3", "view_id": 2}, {"point_uuid": "123", "nonfixated_pixel_x": 419, "nonfixated_pixel_y": 229, "camera_uuid": "e629b23698734e38878f8b71b4ce29dc", "view_id": 0}, {"point_uuid": "126", "nonfixated_pixel_x": 317, "nonfixated_pixel_y": 258, "camera_uuid": "e629b23698734e38878f8b71b4ce29dc", "view_id": 4}, {"point_uuid": "151", "nonfixated_pixel_x": 358, "nonfixated_pixel_y": 290, "camera_uuid": "92433d882a1045149320c629c8183e8d", "view_id": 2}, {"point_uuid": "193", "nonfixated_pixel_x": 311, "nonfixated_pixel_y": 396, "camera_uuid": "92433d882a1045149320c629c8183e8d", "view_id": 7}, {"point_uuid": "306", "nonfixated_pixel_x": 159, "nonfixated_pixel_y": 211, "camera_uuid": "220387d869434246aa396d4d176250b3", "view_id": 4}, {"point_uuid": "342", "nonfixated_pixel_x": 294, "nonfixated_pixel_y": 149, "camera_uuid": "e629b23698734e38878f8b71b4ce29dc", "view_id": 2}, {"point_uuid": "355", "nonfixated_pixel_x": 37, "nonfixated_pixel_y": 169, "camera_uuid": "220387d869434246aa396d4d176250b3", "view_id": 3}, {"point_uuid": "369", "nonfixated_pixel_x": 39, "nonfixated_pixel_y": 158, "camera_uuid": "220387d869434246aa396d4d176250b3", "view_id": 3}, {"point_uuid": "449", "nonfixated_pixel_x": 62, "nonfixated_pixel_y": 170, "camera_uuid": "220387d869434246aa396d4d176250b3", "view_id": 1}, {"point_uuid": "451", "nonfixated_pixel_x": 0, "nonfixated_pixel_y": 317, "camera_uuid": "220387d869434246aa396d4d176250b3", "view_id": 0}, {"point_uuid": "491", "nonfixated_pixel_x": 20, "nonfixated_pixel_y": 179, "camera_uuid": "220387d869434246aa396d4d176250b3", "view_id": 1}, {"point_uuid": "499", "nonfixated_pixel_x": 105, "nonfixated_pixel_y": 187, "camera_uuid": "220387d869434246aa396d4d176250b3", "view_id": 3}, {"point_uuid": "512", "nonfixated_pixel_x": 140, "nonfixated_pixel_y": 172, "camera_uuid": "220387d869434246aa396d4d176250b3", "view_id": 1}, {"point_uuid": "609", "nonfixated_pixel_x": 73, "nonfixated_pixel_y": 191, "camera_uuid": "220387d869434246aa396d4d176250b3", "view_id": 0}, {"point_uuid": "783", "nonfixated_pixel_x": 338, "nonfixated_pixel_y": 220, "camera_uuid": "e629b23698734e38878f8b71b4ce29dc", "view_id": 4}, {"point_uuid": "837", "nonfixated_pixel_x": 207, "nonfixated_pixel_y": 151, "camera_uuid": "e629b23698734e38878f8b71b4ce29dc", "view_id": 0}, {"point_uuid": "840", "nonfixated_pixel_x": 275, "nonfixated_pixel_y": 248, "camera_uuid": "e629b23698734e38878f8b71b4ce29dc", "view_id": 1}, {"point_uuid": "840", "nonfixated_pixel_x": 388, "nonfixated_pixel_y": 225, "camera_uuid": "92433d882a1045149320c629c8183e8d", "view_id": 2}, {"point_uuid": "881", "nonfixated_pixel_x": 426, "nonfixated_pixel_y": 246, "camera_uuid": "e629b23698734e38878f8b71b4ce29dc", "view_id": 1}, {"point_uuid": "886", "nonfixated_pixel_x": 140, "nonfixated_pixel_y": 169, "camera_uuid": "220387d869434246aa396d4d176250b3", "view_id": 0}, {"point_uuid": "918", "nonfixated_pixel_x": 14, "nonfixated_pixel_y": 269, "camera_uuid": "220387d869434246aa396d4d176250b3", "view_id": 3}, {"point_uuid": "955", "nonfixated_pixel_x": 63, "nonfixated_pixel_y": 301, "camera_uuid": "220387d869434246aa396d4d176250b3", "view_id": 0}, {"point_uuid": "1016", "nonfixated_pixel_x": 58, "nonfixated_pixel_y": 163, "camera_uuid": "220387d869434246aa396d4d176250b3", "view_id": 0}, {"point_uuid": "1157", "nonfixated_pixel_x": 384, "nonfixated_pixel_y": 150, "camera_uuid": "e629b23698734e38878f8b71b4ce29dc", "view_id": 0}, {"point_uuid": "1364", "nonfixated_pixel_x": 328, "nonfixated_pixel_y": 192, "camera_uuid": "e629b23698734e38878f8b71b4ce29dc", "view_id": 2}, {"point_uuid": "1385", "nonfixated_pixel_x": 96, "nonfixated_pixel_y": 210, "camera_uuid": "220387d869434246aa396d4d176250b3", "view_id": 1}, {"point_uuid": "1412", "nonfixated_pixel_x": 204, "nonfixated_pixel_y": 257, "camera_uuid": "e629b23698734e38878f8b71b4ce29dc", "view_id": 1}, {"point_uuid": "1438", "nonfixated_pixel_x": 335, "nonfixated_pixel_y": 117, "camera_uuid": "92433d882a1045149320c629c8183e8d", "view_id": 2}]}