{"point_uuid": "1413", "point_location": [9.953176498413086, -7.492491245269775, 2.1581759452819824], "views": [{"point_uuid": "154", "nonfixated_pixel_x": 252, "nonfixated_pixel_y": 240, "camera_uuid": "92433d882a1045149320c629c8183e8d", "view_id": 0}, {"point_uuid": "154", "nonfixated_pixel_x": 253, "nonfixated_pixel_y": 244, "camera_uuid": "e629b23698734e38878f8b71b4ce29dc", "view_id": 1}, {"point_uuid": "154", "nonfixated_pixel_x": 253, "nonfixated_pixel_y": 237, "camera_uuid": "f25ef12a685c4892bb8bd91c8c0bbc27", "view_id": 2}, {"point_uuid": "235", "nonfixated_pixel_x": 272, "nonfixated_pixel_y": 171, "camera_uuid": "f25ef12a685c4892bb8bd91c8c0bbc27", "view_id": 0}, {"point_uuid": "235", "nonfixated_pixel_x": 294, "nonfixated_pixel_y": 165, "camera_uuid": "92433d882a1045149320c629c8183e8d", "view_id": 1}, {"point_uuid": "235", "nonfixated_pixel_x": 275, "nonfixated_pixel_y": 194, "camera_uuid": "e629b23698734e38878f8b71b4ce29dc", "view_id": 2}, {"point_uuid": "376", "nonfixated_pixel_x": 27, "nonfixated_pixel_y": 205, "camera_uuid": "92433d882a1045149320c629c8183e8d", "view_id": 0}, {"point_uuid": "533", "nonfixated_pixel_x": 194, "nonfixated_pixel_y": 312, "camera_uuid": "f25ef12a685c4892bb8bd91c8c0bbc27", "view_id": 0}, {"point_uuid": "533", "nonfixated_pixel_x": 144, "nonfixated_pixel_y": 305, "camera_uuid": "e629b23698734e38878f8b71b4ce29dc", "view_id": 1}, {"point_uuid": "533", "nonfixated_pixel_x": 146, "nonfixated_pixel_y": 274, "camera_uuid": "92433d882a1045149320c629c8183e8d", "view_id": 2}, {"point_uuid": "659", "nonfixated_pixel_x": 272, "nonfixated_pixel_y": 98, "camera_uuid": "92433d882a1045149320c629c8183e8d", "view_id": 0}, {"point_uuid": "659", "nonfixated_pixel_x": 266, "nonfixated_pixel_y": 68, "camera_uuid": "f25ef12a685c4892bb8bd91c8c0bbc27", "view_id": 1}, {"point_uuid": "659", "nonfixated_pixel_x": 266, "nonfixated_pixel_y": 126, "camera_uuid": "e629b23698734e38878f8b71b4ce29dc", "view_id": 2}, {"point_uuid": "822", "nonfixated_pixel_x": 214, "nonfixated_pixel_y": 335, "camera_uuid": "92433d882a1045149320c629c8183e8d", "view_id": 0}, {"point_uuid": "822", "nonfixated_pixel_x": 308, "nonfixated_pixel_y": 305, "camera_uuid": "f25ef12a685c4892bb8bd91c8c0bbc27", "view_id": 1}, {"point_uuid": "822", "nonfixated_pixel_x": 296, "nonfixated_pixel_y": 326, "camera_uuid": "e629b23698734e38878f8b71b4ce29dc", "view_id": 2}, {"point_uuid": "1412", "nonfixated_pixel_x": 336, "nonfixated_pixel_y": 197, "camera_uuid": "92433d882a1045149320c629c8183e8d", "view_id": 0}]}